illumio/__init__.py
illumio/_version.py
illumio/events.py
illumio/exceptions.py
illumio/pce.py
illumio/pce.pyi
illumio/py.typed
illumio/secpolicy.py
illumio/accessmanagement/__init__.py
illumio/accessmanagement/user.py
illumio/explorer/__init__.py
illumio/explorer/trafficanalysis.py
illumio/infrastructure/__init__.py
illumio/infrastructure/containercluster.py
illumio/infrastructure/network.py
illumio/infrastructure/secureconnectgateway.py
illumio/policyobjects/__init__.py
illumio/policyobjects/iplist.py
illumio/policyobjects/label.py
illumio/policyobjects/securityprincipal.py
illumio/policyobjects/service.py
illumio/policyobjects/virtualserver.py
illumio/policyobjects/virtualservice.py
illumio/rules/__init__.py
illumio/rules/actor.py
illumio/rules/enforcementboundary.py
illumio/rules/iptablesrule.py
illumio/rules/rule.py
illumio/rules/ruleset.py
illumio/util/__init__.py
illumio/util/constants.py
illumio/util/functions.py
illumio/util/jsonutils.py
illumio/vulnerabilities/__init__.py
illumio/vulnerabilities/vulnerability.py
illumio/vulnerabilities/vulnerabilityreport.py
illumio/workloads/__init__.py
illumio/workloads/pairingprofile.py
illumio/workloads/ven.py
illumio/workloads/workload.py
illumio-1.1.3.dist-info/LICENSE
illumio-1.1.3.dist-info/METADATA
illumio-1.1.3.dist-info/WHEEL
illumio-1.1.3.dist-info/top_level.txt
illumio-1.1.3.dist-info/RECORD
