Metadata-Version: 2.1
Name: illumio
Version: 1.1.3
Summary: REST API client framework to manage the Illumio Core Policy Compute Engine
Home-page: https://github.com/illumio/illumio-py
Author: Illumio
Author-email: app-integrations@illumio.com
License: UNKNOWN
Platform: UNKNOWN
Classifier: Development Status :: 4 - Beta
Classifier: License :: OSI Approved :: Apache Software License
Classifier: Programming Language :: Python :: 3 :: Only
Classifier: Programming Language :: Python :: 3.6
Classifier: Programming Language :: Python :: 3.7
Classifier: Programming Language :: Python :: 3.8
Classifier: Programming Language :: Python :: 3.9
Classifier: Programming Language :: Python :: 3.10
License-File: LICENSE
